Metadata-Version: 2.1
Name: vcache
Version: 0.0.7
Summary: Python implementation of go-redis/cache
Home-page: https://github.com/vimiix/vcache
Author: vimiix
Author-email: vimiix.py@gmail.com
License: MIT
Keywords: cache,localcache
Platform: UNKNOWN
Classifier: Programming Language :: Python
Classifier: Programming Language :: Python :: 3.7
Classifier: Intended Audience :: Developers
Classifier: License :: OSI Approved :: MIT License
Classifier: Operating System :: OS Independent
